lego_bridge.cpython-39-x86_64-linux-gnu.h
lego_bridge.cpython-39-x86_64-linux-gnu.so
certbot_dns_multi/__init__.py
certbot_dns_multi/_version.py
certbot_dns_multi/_internal/dns_multi.py
certbot_dns_multi/_internal/bridge/go.mod
certbot_dns_multi/_internal/bridge/go.sum
certbot_dns_multi/_internal/bridge/main.c
certbot_dns_multi/_internal/bridge/main.go
certbot_dns_multi-4.30.1.dist-info/METADATA
certbot_dns_multi-4.30.1.dist-info/WHEEL
certbot_dns_multi-4.30.1.dist-info/entry_points.txt
certbot_dns_multi-4.30.1.dist-info/top_level.txt
certbot_dns_multi-4.30.1.dist-info/RECORD
certbot_dns_multi-4.30.1.dist-info/licenses/LICENSE.txt
