Metadata-Version: 2.4
Name: certbot-dns-multi
Version: 4.30.1
Summary: Certbot DNS plugin supporting multiple providers, using github.com/go-acme/lego
License: MIT
Requires-Python: >=3.9
License-File: LICENSE.txt
Requires-Dist: certbot>=1.12.0
Requires-Dist: acme>=1.12.0
Requires-Dist: josepy>=1.1.0
Provides-Extra: dev
Requires-Dist: black>=22.10.0; extra == "dev"
Requires-Dist: flake8>=5.0.4; extra == "dev"
Dynamic: license-file
Dynamic: requires-dist
